[
    {
        "model": "competition.division",
        "pk": null,
        "fields": {
            "meet": 1,
            "level": null,
            "name": "6 & up d1",
            "short_name": "6 & up",
            "min_age": 5,
            "max_age": 19,
            "event_award_count": 0,
            "all_around_award_count": 0
        }
    },
    {
        "model": "competition.division",
        "pk": null,
        "fields": {
            "meet": 1,
            "level": null,
            "name": "6 & up d2",
            "short_name": "6 & up",
            "min_age": 5,
            "max_age": 19,
            "event_award_count": 0,
            "all_around_award_count": 0
        }
    },
    {
        "model": "competition.division",
        "pk": null,
        "fields": {
            "meet": 1,
            "level": null,
            "name": "7 & up d1",
            "short_name": "7 & up",
            "min_age": 7,
            "max_age": 19,
            "event_award_count": 0,
            "all_around_award_count": 0
        }
    },
    {
        "model": "competition.division",
        "pk": null,
        "fields": {
            "meet": 1,
            "level": null,
            "name": "7 & up d2",
            "short_name": "7 & up",
            "min_age": 7,
            "max_age": 19,
            "event_award_count": 0,
            "all_around_award_count": 0
        }
    },
    {
        "model": "competition.division",
        "pk": null,
        "fields": {
            "meet": 1,
            "level": null,
            "name": "8 & up d1",
            "short_name": "8 & up",
            "min_age": 8,
            "max_age": 19,
            "event_award_count": 0,
            "all_around_award_count": 0
        }
    },
    {
        "model": "competition.division",
        "pk": null,
        "fields": {
            "meet": 1,
            "level": null,
            "name": "8 & up d2",
            "short_name": "8 & up",
            "min_age": 8,
            "max_age": 19,
            "event_award_count": 0,
            "all_around_award_count": 0
        }
    },
    {
        "model": "competition.division",
        "pk": null,
        "fields": {
            "meet": 1,
            "level": null,
            "name": "10 & up d1",
            "short_name": "10 & up",
            "min_age": 10,
            "max_age": 19,
            "event_award_count": 0,
            "all_around_award_count": 0
        }
    },
    {
        "model": "competition.division",
        "pk": null,
        "fields": {
            "meet": 1,
            "level": null,
            "name": "10 & up d2",
            "short_name": "10 & up",
            "min_age": 10,
            "max_age": 19,
            "event_award_count": 0,
            "all_around_award_count": 0
        }
    },
    {
        "model": "competition.division",
        "pk": null,
        "fields": {
            "meet": 1,
            "level": null,
            "name": "11 & up",
            "short_name": "11 & up",
            "min_age": 11,
            "max_age": 19,
            "event_award_count": 0,
            "all_around_award_count": 0
        }
    },
    {
        "model": "competition.division",
        "pk": null,
        "fields": {
            "meet": 1,
            "level": null,
            "name": "11 & up",
            "short_name": "11 & up",
            "min_age": 11,
            "max_age": 19,
            "event_award_count": 0,
            "all_around_award_count": 0
        }
    },
    {
        "model": "competition.division",
        "pk": null,
        "fields": {
            "meet": 1,
            "level": null,
            "name": "13 & up",
            "short_name": "13 & up",
            "min_age": 13,
            "max_age": 19,
            "event_award_count": 0,
            "all_around_award_count": 0
        }
    },
    {
        "model": "competition.division",
        "pk": null,
        "fields": {
            "meet": 1,
            "level": null,
            "name": "15 & up",
            "short_name": "15 & up",
            "min_age": 15,
            "max_age": 19,
            "event_award_count": 0,
            "all_around_award_count": 0
        }
    }
]